{"type":"Dialog","props":{"width":720,"height":1280},"compId":2,"child":[{"type":"Image","props":{"y":261,"x":47,"width":626,"skin":"comp/jinpinyouxidi.png","sizeGrid":"10,10,10,10","height":685},"compId":16},{"type":"Image","props":{"y":375,"x":70,"width":580,"skin":"comp/neirongdi.png","sizeGrid":"30,54,46,54","height":551},"compId":17},{"type":"Image","props":{"y":262,"x":0,"width":720,"skin":"comp/title_huang.png","sizeGrid":"0,73,0,62"},"compId":4},{"type":"Sprite","props":{"y":246,"x":586,"texture":"comp/xue2.png"},"compId":5},{"type":"Sprite","props":{"y":240,"x":18,"texture":"comp/xue1.png"},"compId":6},{"type":"Label","props":{"y":402,"x":100,"width":520,"text":"1.左右移动躲避旗帜，雪球，障碍","height":34,"fontSize":34,"color":"#2580a0"},"compId":10},{"type":"Label","props":{"y":452,"x":100,"wordWrap":true,"width":520,"text":"2.加速带和跳台可以获得更快的速度，直接越过障碍","height":34,"fontSize":34,"color":"#2580a0"},"compId":11},{"type":"Label","props":{"y":592,"x":100,"wordWrap":true,"width":520,"text":"4.小火箭可以使玩家立即获得更快的速度，合理使用小火箭可以持续高速滑行","padding":"0","height":34,"fontSize":34,"color":"#2580a0"},"compId":12},{"type":"Label","props":{"y":539,"x":100,"wordWrap":true,"width":520,"text":"3.碰撞雪花可以获得能量用来加速","height":34,"fontSize":34,"color":"#2580a0"},"compId":14},{"type":"Label","props":{"y":278,"x":106,"width":507,"text":"高山速降滑雪玩法说明","height":47,"fontSize":47,"color":"#ffffff","align":"center"},"compId":8},{"type":"Label","props":{"y":952,"x":43,"width":633,"valign":"middle","underline":true,"text":"我知道了","name":"close","mouseEnabled":true,"height":55,"fontSize":35,"color":"#ffffff","align":"center"},"compId":15},{"type":"Label","props":{"y":709,"x":100,"wordWrap":true,"width":520,"text":"5.小道消息，超越其他玩家可以获得额外金币，坚持到最后获得的金币越多","height":34,"fontSize":34,"color":"#2580a0"},"compId":18},{"type":"Button","props":{"var":"btnrewan","top":85,"stateNum":1,"skin":"comp/tuichu1.png","runtime":"script/gui/ScaleButton.ts","right":35,"anchorY":0.5,"anchorX":0.5},"compId":19}],"loadList":["comp/jinpinyouxidi.png","comp/neirongdi.png","comp/title_huang.png","comp/xue2.png","comp/xue1.png","comp/tuichu1.png"],"loadList3D":[]}